msgfy/__init__.py
msgfy/__version__.py
msgfy/py.typed
msgfy-0.2.1.dist-info/LICENSE
msgfy-0.2.1.dist-info/METADATA
msgfy-0.2.1.dist-info/WHEEL
msgfy-0.2.1.dist-info/top_level.txt
msgfy-0.2.1.dist-info/RECORD
