Metadata-Version: 2.1
Name: msgfy
Version: 0.2.1
Summary: msgfy is a Python library for convert Exception instance to a human-readable error message.
Home-page: https://github.com/thombashi/msgfy
Author: Tsuyoshi Hombashi
Author-email: tsuyoshi.hombashi@gmail.com
License: MIT License
Project-URL: Source, https://github.com/thombashi/msgfy
Project-URL: Tracker, https://github.com/thombashi/msgfy/issues
Keywords: error
Classifier: Development Status :: 4 - Beta
Classifier: Intended Audience :: Developers
Classifier: Intended Audience :: Information Technology
Classifier: License :: OSI Approved :: MIT License
Classifier: Operating System :: OS Independent
Classifier: Programming Language :: Python :: 3
Classifier: Programming Language :: Python :: 3.7
Classifier: Programming Language :: Python :: 3.8
Classifier: Programming Language :: Python :: 3.9
Classifier: Programming Language :: Python :: 3.10
Classifier: Programming Language :: Python :: 3.11
Classifier: Programming Language :: Python :: 3 :: Only
Classifier: Programming Language :: Python :: Implementation :: CPython
Classifier: Programming Language :: Python :: Implementation :: PyPy
Classifier: Topic :: Software Development :: Libraries
Classifier: Topic :: Software Development :: Libraries :: Python Modules
Classifier: Topic :: Text Processing
Classifier: Typing :: Typed
Requires-Python: >=3.7
License-File: LICENSE
Provides-Extra: test
Requires-Dist: pytest>=6.0.1; extra == "test"
Requires-Dist: pytest-md-report>=0.4.1; extra == "test"
